[
  {
    "code": "1",
    "name": "CAMSHAFT AND CASE"
  },
  {
    "code": "2",
    "name": "CLUTCH (FOR M32 MANUAL TRANSMISSION,RPO MGP)"
  },
  {
    "code": "3",
    "name": "CONNECTING ROD"
  },
  {
    "code": "4",
    "name": "CONNECTING ROD BEARINGS"
  },
  {
    "code": "5",
    "name": "CRANKSHAFT"
  },
  {
    "code": "6",
    "name": "CRANKSHAFT BEARINGS AND SEALS"
  },
  {
    "code": "7",
    "name": "CRANKSHAFT PULLEY"
  },
  {
    "code": "8",
    "name": "CRANKSHAFT PULSE GENERATOR WHEEL"
  },
  {
    "code": "9",
    "name": "CYLINDER BLOCK"
  },
  {
    "code": "10",
    "name": "CYLINDER BLOCK PLUGS"
  },
  {
    "code": "11",
    "name": "CYLINDER HEAD, PLUGS AND GASKET"
  },
  {
    "code": "12",
    "name": "ENGINE ASSEMBLY"
  },
  {
    "code": "13",
    "name": "ENGINE COVER"
  },
  {
    "code": "14",
    "name": "ENGINE LIFTING HANGER"
  },
  {
    "code": "15",
    "name": "ENGINE MOUNTINGS (FOR M32 MANUAL TRANSMISSION,RPO MGP)"
  },
  {
    "code": "16",
    "name": "ENGINE MOUNTINGS (FOR 9T45 AUTOMATIC TRANSMISSION,RPO Mi7)"
  },
  {
    "code": "17",
    "name": "ENGINE,STRIPPED"
  },
  {
    "code": "18",
    "name": "FLEXPLATE AND FITTINGS"
  },
  {
    "code": "19",
    "name": "FLYWHEEL AND FITTINGS"
  },
  {
    "code": "20",
    "name": "FRONT COVER"
  },
  {
    "code": "21",
    "name": "OIL COOLER PIPES AND HOSES"
  },
  {
    "code": "22",
    "name": "OIL FILLER"
  },
  {
    "code": "23",
    "name": "OIL FILTER"
  },
  {
    "code": "24",
    "name": "OIL LEVEL INDICATOR"
  },
  {
    "code": "25",
    "name": "OIL PAN AND FITTINGS"
  },
  {
    "code": "26",
    "name": "OIL PIPES,VALVES AND FITTINGS"
  },
  {
    "code": "27",
    "name": "OIL PUMP AND BALANCE SHAFT"
  },
  {
    "code": "28",
    "name": "PISTON AND RINGS"
  },
  {
    "code": "29",
    "name": "ROCKER ARM"
  },
  {
    "code": "30",
    "name": "TIMING CHAIN,GEAR AND PULLEYS"
  },
  {
    "code": "31",
    "name": "VALVE LIFTER"
  },
  {
    "code": "32",
    "name": "VALVES, INLET AND EXHAUST"
  }
]