[
  {
    "call": "1",
    "part": "55485697",
    "desc": "MAINSHAFT,UPPER,20 TEETH (FOR M32 MANUAL TRANSMISSION,RPO MGP) (FINAL DRIVE RATIO 3.65)",
    "qty": "1",
    "usage": "",
    "range": "",
    "positions": [],
    "reach": [],
    "history": []
  },
  {
    "call": "1",
    "part": "55486566",
    "desc": "MAINSHAFT,UPPER,20 TEETH (FOR M32 MANUAL TRANSMISSION,RPO MGP/MGW) (FINAL DRIVE RATIO 3.35)",
    "qty": "1",
    "usage": "",
    "range": "",
    "positions": [],
    "reach": [],
    "history": []
  },
  {
    "call": "1",
    "part": "55486567",
    "desc": "MAINSHAFT,UPPER,18 TEETH (FOR M32 MANUAL TRANSMISSION,RPO MGR) (FINAL DRIVE RATIO 3.83)",
    "qty": "1",
    "usage": "",
    "range": "",
    "positions": [],
    "reach": [],
    "history": []
  },
  {
    "call": "1",
    "part": "(55599235)",
    "desc": "MAINSHAFT,UPPER,20 TEETH (FOR M35 MANUAL TRANSMISSION,RPO MOP) (FINAL DRIVE RATIO 3.65) (NLS.- USE 55507186)",
    "qty": "1",
    "usage": "",
    "range": "",
    "positions": [],
    "reach": [],
    "history": []
  },
  {
    "call": "1",
    "part": "55507186",
    "desc": "MAINSHAFT,UPPER,20 TEETH (FOR M35 MANUAL TRANSMISSION,RPO MOP) (FINAL DRIVE RATIO 3.65)",
    "qty": "1",
    "usage": "",
    "range": "",
    "positions": [],
    "reach": [],
    "history": []
  },
  {
    "call": "2",
    "part": "55597871",
    "desc": "BEARING,MAINSHAFT,FRONT",
    "qty": "1",
    "usage": "",
    "range": "",
    "positions": [],
    "reach": [],
    "history": []
  },
  {
    "call": "3",
    "part": "55564126",
    "desc": "RING,RETAINING,BEARING,MAINSHAFT,41 X 2.13MM",
    "qty": "1",
    "usage": "",
    "range": "",
    "positions": [],
    "reach": [],
    "history": []
  },
  {
    "call": "3",
    "part": "55564127",
    "desc": "RING,RETAINING,BEARING,MAINSHAFT,41 X 2.11MM",
    "qty": "1",
    "usage": "",
    "range": "",
    "positions": [],
    "reach": [],
    "history": []
  },
  {
    "call": "3",
    "part": "55564128",
    "desc": "RING,RETAINING,BEARING,MAINSHAFT,41 X 2.09MM",
    "qty": "1",
    "usage": "",
    "range": "",
    "positions": [],
    "reach": [],
    "history": []
  },
  {
    "call": "3",
    "part": "55564129",
    "desc": "RING,RETAINING,BEARING,MAINSHAFT,41 X 2.07MM",
    "qty": "1",
    "usage": "",
    "range": "",
    "positions": [],
    "reach": [],
    "history": []
  },
  {
    "call": "4",
    "part": "55598858",
    "desc": "GEAR,REVERSE,39 TEETH,MAINSHAFT,UPPER (FOR M32 MANUAL TRANSMISSION,RPO MGP/MGR)",
    "qty": "1",
    "usage": "",
    "range": "",
    "positions": [],
    "reach": [],
    "history": []
  },
  {
    "call": "4",
    "part": "55485147",
    "desc": "GEAR,REVERSE,42 TEETH,MAINSHAFT,UPPER (FOR M32 MANUAL TRANSMISSION,RPO MGW)",
    "qty": "1",
    "usage": "",
    "range": "",
    "positions": [],
    "reach": [],
    "history": []
  },
  {
    "call": "4",
    "part": "55598858",
    "desc": "GEAR,REVERSE,39 TEETH,MAINSHAFT,UPPER (FOR M35 MANUAL TRANSMISSION,RPO MOP)",
    "qty": "1",
    "usage": "",
    "range": "",
    "positions": [],
    "reach": [],
    "history": []
  },
  {
    "call": "5",
    "part": "55181050",
    "desc": "BEARING,NEEDLE,44 X 49 X 27.2MM,MAINSHAFT,REVERSE GEAR",
    "qty": "1",
    "usage": "",
    "range": "",
    "positions": [],
    "reach": [],
    "history": []
  },
  {
    "call": "6",
    "part": "(55566681)",
    "desc": "RING,SYNCHRONIZER,REVERSE GEAR (NLS.- USE 55503135)",
    "qty": "1",
    "usage": "",
    "range": "",
    "positions": [],
    "reach": [],
    "history": []
  },
  {
    "call": "7",
    "part": "55599672",
    "desc": "SYNCHRONIZER,ASSY,REVERSE GEAR",
    "qty": "1",
    "usage": "",
    "range": "",
    "positions": [],
    "reach": [],
    "history": []
  },
  {
    "call": "8",
    "part": "55352152",
    "desc": "-KEY,SYNCHRONIZER CONE,REVERSE GEAR",
    "qty": "3",
    "usage": "",
    "range": "",
    "positions": [],
    "reach": [],
    "history": []
  },
  {
    "call": "9",
    "part": "55181028",
    "desc": "SPACER,MAINSHAFT",
    "qty": "1",
    "usage": "",
    "range": "",
    "positions": [],
    "reach": [],
    "history": []
  },
  {
    "call": "10",
    "part": "55564132",
    "desc": "RING,RETAINING,HUB,CLUTCH,REVERSE GEAR,38 X 2MM",
    "qty": "1",
    "usage": "",
    "range": "",
    "positions": [],
    "reach": [],
    "history": []
  },
  {
    "call": "11",
    "part": "(55580388)",
    "desc": "GEAR,THIRD SPEED,56 TEETH,MAINSHAFT,UPPER (FOR M32 MANUAL TRANSMISSION,RPO MGP) (NLS.- USE 55599233)",
    "qty": "1",
    "usage": "",
    "range": "",
    "positions": [],
    "reach": [],
    "history": []
  },
  {
    "call": "11",
    "part": "55599233",
    "desc": "GEAR,THIRD SPEED,56 TEETH,MAINSHAFT,UPPER (FOR M32 MANUAL TRANSMISSION,RPO MGP)",
    "qty": "1",
    "usage": "",
    "range": "",
    "positions": [],
    "reach": [],
    "history": []
  },
  {
    "call": "11",
    "part": "55580390",
    "desc": "GEAR,THIRD SPEED,59 TEETH,MAINSHAFT,UPPER (FOR M32 MANUAL TRANSMISSION,RPO MGR)",
    "qty": "1",
    "usage": "",
    "range": "",
    "positions": [],
    "reach": [],
    "history": []
  },
  {
    "call": "11",
    "part": "55580391",
    "desc": "GEAR,THIRD SPEED,55 TEETH,MAINSHAFT,UPPER (FOR M32 MANUAL TRANSMISSION,RPO MGW)",
    "qty": "1",
    "usage": "",
    "range": "",
    "positions": [],
    "reach": [],
    "history": []
  },
  {
    "call": "11",
    "part": "55599233",
    "desc": "GEAR,THIRD SPEED,56 TEETH,MAINSHAFT,UPPER (FOR M35 MANUAL TRANSMISSION,RPO MOP)",
    "qty": "1",
    "usage": "",
    "range": "",
    "positions": [],
    "reach": [],
    "history": []
  },
  {
    "call": "12",
    "part": "55502864",
    "desc": "BEARING,NEEDLE,40 X 45 X 26.3MM,MAINSHAFT,THIRD GEAR",
    "qty": "1",
    "usage": "",
    "range": "",
    "positions": [],
    "reach": [],
    "history": []
  },
  {
    "call": "13",
    "part": "55599121",
    "desc": "RING,SYNCHRONIZER,THIRD AND FOURTH GEAR",
    "qty": "2",
    "usage": "",
    "range": "(C)      -J8999999\n(C)      -JG999999",
    "positions": [],
    "reach": [],
    "history": []
  },
  {
    "call": "13",
    "part": "55512804",
    "desc": "RING,SYNCHRONIZER,THIRD AND FOURTH GEAR",
    "qty": "2",
    "usage": "",
    "range": "(C)  K8000001-\n(C)  KG000001-",
    "positions": [],
    "reach": [],
    "history": []
  },
  {
    "call": "14",
    "part": "55599120",
    "desc": "SYNCHRONIZER,ASSY.,THIRD AND FOURTH GEAR",
    "qty": "1",
    "usage": "(D)      -18062019",
    "range": "",
    "positions": [],
    "reach": [],
    "history": []
  },
  {
    "call": "14",
    "part": "55510365",
    "desc": "SYNCHRONIZER,ASSY.,THIRD AND FOURTH GEAR",
    "qty": "1",
    "usage": "(D)  19062019-",
    "range": "",
    "positions": [],
    "reach": [],
    "history": []
  },
  {
    "call": "15",
    "part": "55352152",
    "desc": "-KEY,SYNCHRONIZER CONE,THIRD AND FOURTH GEAR",
    "qty": "3",
    "usage": "",
    "range": "",
    "positions": [],
    "reach": [],
    "history": []
  },
  {
    "call": "16",
    "part": "55564131",
    "desc": "RING,RETAINING,CLUTCH AND HUB,ASSY.,THIRD AND FOURTH GEAR,32 X 2MM",
    "qty": "1",
    "usage": "",
    "range": "",
    "positions": [],
    "reach": [],
    "history": []
  },
  {
    "call": "17",
    "part": "55182039",
    "desc": "GEAR,FOURTH SPEED,49 TEETH,MAINSHAFT,UPPER (FOR M32 MANUAL TRANSMISSION,RPO MGP)",
    "qty": "1",
    "usage": "",
    "range": "",
    "positions": [],
    "reach": [],
    "history": []
  },
  {
    "call": "17",
    "part": "55491400",
    "desc": "GEAR,FOURTH SPEED,48 TEETH,MAINSHAFT,UPPER (FOR M32 MANUAL TRANSMISSION,RPO MGR)",
    "qty": "1",
    "usage": "",
    "range": "",
    "positions": [],
    "reach": [],
    "history": []
  },
  {
    "call": "17",
    "part": "55491401",
    "desc": "GEAR,FOURTH SPEED,61 TEETH,MAINSHAFT,UPPER (FOR M32 MANUAL TRANSMISSION,RPO MGW)",
    "qty": "1",
    "usage": "",
    "range": "",
    "positions": [],
    "reach": [],
    "history": []
  },
  {
    "call": "17",
    "part": "55599242",
    "desc": "GEAR,FOURTH SPEED,47 TEETH,MAINSHAFT,UPPER (FOR M35 MANUAL TRANSMISSION,RPO MOP)",
    "qty": "1",
    "usage": "",
    "range": "",
    "positions": [],
    "reach": [],
    "history": []
  },
  {
    "call": "18",
    "part": "55567019",
    "desc": "BEARING,NEEDLE,34 X 38.5 X 23.05MM,MAINSHAFT,FOURTH GEAR",
    "qty": "1",
    "usage": "",
    "range": "",
    "positions": [],
    "reach": [],
    "history": []
  },
  {
    "call": "19",
    "part": "55598860",
    "desc": "WASHER,THRUST",
    "qty": "1",
    "usage": "",
    "range": "",
    "positions": [],
    "reach": [],
    "history": []
  },
  {
    "call": "20",
    "part": "55597874",
    "desc": "RETAINER",
    "qty": "1",
    "usage": "",
    "range": "",
    "positions": [],
    "reach": [],
    "history": []
  },
  {
    "call": "21",
    "part": "55599099",
    "desc": "RING,RETAINING,2.21MM THICK,BEARING,MAINSHAFT,UPPER,REAR",
    "qty": "1",
    "usage": "",
    "range": "",
    "positions": [],
    "reach": [],
    "history": []
  },
  {
    "call": "21",
    "part": "55599100",
    "desc": "RING,RETAINING,2.24MM THICK,BEARING,MAINSHAFT,UPPER,REAR",
    "qty": "1",
    "usage": "",
    "range": "",
    "positions": [],
    "reach": [],
    "history": []
  },
  {
    "call": "21",
    "part": "55599101",
    "desc": "RING,RETAINING,2.27MM THICK,BEARING,MAINSHAFT,UPPER,REAR",
    "qty": "1",
    "usage": "",
    "range": "",
    "positions": [],
    "reach": [],
    "history": []
  },
  {
    "call": "21",
    "part": "55599102",
    "desc": "RING,RETAINING,2.30MM THICK,BEARING,MAINSHAFT,UPPER,REAR",
    "qty": "1",
    "usage": "",
    "range": "",
    "positions": [],
    "reach": [],
    "history": []
  },
  {
    "call": "21",
    "part": "55599103",
    "desc": "RING,RETAINING,2.33MM THICK,BEARING,MAINSHAFT,UPPER,REAR",
    "qty": "1",
    "usage": "",
    "range": "",
    "positions": [],
    "reach": [],
    "history": []
  },
  {
    "call": "21",
    "part": "55599104",
    "desc": "RING,RETAINING,2.36MM THICK,BEARING,MAINSHAFT,UPPER,REAR",
    "qty": "1",
    "usage": "",
    "range": "",
    "positions": [],
    "reach": [],
    "history": []
  },
  {
    "call": "21",
    "part": "55599105",
    "desc": "RING,RETAINING,2.39MM THICK,BEARING,MAINSHAFT,UPPER,REAR",
    "qty": "1",
    "usage": "",
    "range": "",
    "positions": [],
    "reach": [],
    "history": []
  },
  {
    "call": "21",
    "part": "55599106",
    "desc": "RING,RETAINING,2.42MM THICK,BEARING,MAINSHAFT,UPPER,REAR",
    "qty": "1",
    "usage": "",
    "range": "",
    "positions": [],
    "reach": [],
    "history": []
  }
]