[
  {
    "call": "2",
    "part": "(11588747)",
    "desc": "SCREW,HEX.HD.,M10 X 76 (NLS.- USE YR00067480)",
    "qty": "5",
    "usage": "",
    "range": "",
    "positions": [],
    "reach": [],
    "history": []
  },
  {
    "call": "3",
    "part": "11546378",
    "desc": "NUT,HEX.,M10",
    "qty": "1",
    "usage": "",
    "range": "",
    "positions": [],
    "reach": [],
    "history": []
  },
  {
    "call": "4",
    "part": "11546405",
    "desc": "SCREW,HEX.HD.,M10 X 45",
    "qty": "3",
    "usage": "",
    "range": "",
    "positions": [],
    "reach": [],
    "history": []
  },
  {
    "call": "5",
    "part": "(11589276)",
    "desc": "SCREW,HEX.HD.,M12 X 55 (NLS.- USE YR00146980)",
    "qty": "1",
    "usage": "",
    "range": "",
    "positions": [],
    "reach": [],
    "history": []
  },
  {
    "call": "6",
    "part": "90351708",
    "desc": "SLEEVE",
    "qty": "2",
    "usage": "",
    "range": "",
    "positions": [],
    "reach": [],
    "history": []
  },
  {
    "call": "7",
    "part": "(93165267)",
    "desc": "COMPOUND,SEALING,THREEBOND 1227,80ML,TRANSMISSION (NLS.- USE 1679592380) (IDENT SC11)",
    "qty": "AR",
    "usage": "",
    "range": "",
    "positions": [],
    "reach": [],
    "history": []
  },
  {
    "call": "7",
    "part": "90542117",
    "desc": "LOCKING COMPOUND,50ML,SCREW (IDENT SC18)",
    "qty": "AR",
    "usage": "",
    "range": "",
    "positions": [],
    "reach": [],
    "history": []
  }
]