[
  {
    "call": "1",
    "part": "39114737",
    "desc": "HOSE,RADIATOR INLET",
    "qty": "1",
    "usage": "",
    "range": "",
    "positions": [],
    "reach": [],
    "history": []
  },
  {
    "call": "2",
    "part": "13162322",
    "desc": "CLAMP,38MM DIA.",
    "qty": "1",
    "usage": "",
    "range": "",
    "positions": [],
    "reach": [],
    "history": []
  },
  {
    "call": "3",
    "part": "39017746",
    "desc": "CLIP (FOR 9T45 AUTOMATIC TRANSMISSION,RPO Mi7)",
    "qty": "1",
    "usage": "",
    "range": "",
    "positions": [],
    "reach": [],
    "history": []
  },
  {
    "call": "4",
    "part": "39114738",
    "desc": "HOSE,RADIATOR OUTLET",
    "qty": "1",
    "usage": "",
    "range": "",
    "positions": [],
    "reach": [],
    "history": []
  },
  {
    "call": "5",
    "part": "13162312",
    "desc": "CLAMP,42MM ID.",
    "qty": "1",
    "usage": "",
    "range": "",
    "positions": [],
    "reach": [],
    "history": []
  },
  {
    "call": "6",
    "part": "39114740",
    "desc": "HOSE,ASSY.,FEED,LOWER",
    "qty": "1",
    "usage": "",
    "range": "",
    "positions": [],
    "reach": [],
    "history": []
  },
  {
    "call": "7",
    "part": "90572594",
    "desc": "CLAMP,HOSE,27MM",
    "qty": "1",
    "usage": "",
    "range": "",
    "positions": [],
    "reach": [],
    "history": []
  },
  {
    "call": "8",
    "part": "39114741",
    "desc": "HOSE",
    "qty": "1",
    "usage": "",
    "range": "",
    "positions": [],
    "reach": [],
    "history": []
  },
  {
    "call": "9",
    "part": "90572590",
    "desc": "CLAMP,HOSE,23MM",
    "qty": "1",
    "usage": "",
    "range": "",
    "positions": [],
    "reach": [],
    "history": []
  },
  {
    "call": "10",
    "part": "(39227934)",
    "desc": "HOSE,ASSY.,FEED (NLS.- USE 39227934)",
    "qty": "1",
    "usage": "",
    "range": "",
    "positions": [],
    "reach": [],
    "history": []
  },
  {
    "call": "11",
    "part": "39171876",
    "desc": "-CLIP",
    "qty": "1",
    "usage": "",
    "range": "",
    "positions": [],
    "reach": [],
    "history": []
  },
  {
    "call": "12",
    "part": "90572594",
    "desc": "CLAMP,HOSE,27MM",
    "qty": "1",
    "usage": "",
    "range": "",
    "positions": [],
    "reach": [],
    "history": []
  },
  {
    "call": "13",
    "part": "39227936",
    "desc": "PIPE,ASSY.,WATER,TURBOCHARGER,FEED",
    "qty": "1",
    "usage": "",
    "range": "",
    "positions": [],
    "reach": [],
    "history": []
  },
  {
    "call": "14",
    "part": "13136378",
    "desc": "-CLIP",
    "qty": "1",
    "usage": "",
    "range": "",
    "positions": [],
    "reach": [],
    "history": []
  },
  {
    "call": "15",
    "part": "9164269",
    "desc": "-STRAP,RETAINING",
    "qty": "1",
    "usage": "",
    "range": "",
    "positions": [],
    "reach": [],
    "history": []
  },
  {
    "call": "16",
    "part": "(90467904)",
    "desc": "CLAMP,HOSE,13MM ID. (NLS.- NO REPLACEMENT PART)",
    "qty": "1",
    "usage": "",
    "range": "",
    "positions": [],
    "reach": [],
    "history": []
  },
  {
    "call": "17",
    "part": "39137609",
    "desc": "BRACKET",
    "qty": "1",
    "usage": "",
    "range": "",
    "positions": [],
    "reach": [],
    "history": []
  },
  {
    "call": "18",
    "part": "11570136",
    "desc": "SCREW,M6 X 23 (USED WITH LOCTITE)",
    "qty": "1",
    "usage": "",
    "range": "",
    "positions": [],
    "reach": [],
    "history": []
  },
  {
    "call": "19",
    "part": "39140493",
    "desc": "BRACKET",
    "qty": "1",
    "usage": "",
    "range": "",
    "positions": [],
    "reach": [],
    "history": []
  },
  {
    "call": "20",
    "part": "(11519374)",
    "desc": "SCREW,M6 X 12 (NLS.- USE YR00154580)",
    "qty": "1",
    "usage": "",
    "range": "",
    "positions": [],
    "reach": [],
    "history": []
  },
  {
    "call": "21",
    "part": "39179625",
    "desc": "HOSE,ASSY.,FEED",
    "qty": "1",
    "usage": "",
    "range": "",
    "positions": [],
    "reach": [],
    "history": []
  },
  {
    "call": "22",
    "part": "(90467904)",
    "desc": "CLAMP,HOSE,13MM ID. (NLS.- NO REPLACEMENT PART)",
    "qty": "2",
    "usage": "",
    "range": "",
    "positions": [],
    "reach": [],
    "history": []
  },
  {
    "call": "23",
    "part": "39224972",
    "desc": "HOSE,ASSY.,FEED",
    "qty": "1",
    "usage": "",
    "range": "",
    "positions": [],
    "reach": [],
    "history": []
  },
  {
    "call": "24",
    "part": "13136378",
    "desc": "-CLIP",
    "qty": "1",
    "usage": "",
    "range": "",
    "positions": [],
    "reach": [],
    "history": []
  },
  {
    "call": "25",
    "part": "39114742",
    "desc": "HOSE,ASSY.,RETURN",
    "qty": "1",
    "usage": "",
    "range": "",
    "positions": [],
    "reach": [],
    "history": []
  },
  {
    "call": "26",
    "part": "90572594",
    "desc": "CLAMP,HOSE,27MM",
    "qty": "3",
    "usage": "",
    "range": "",
    "positions": [],
    "reach": [],
    "history": []
  },
  {
    "call": "27",
    "part": "39225786",
    "desc": "SEPARATOR,AIR",
    "qty": "1",
    "usage": "",
    "range": "",
    "positions": [],
    "reach": [],
    "history": []
  },
  {
    "call": "28",
    "part": "39207000",
    "desc": "BRACKET",
    "qty": "1",
    "usage": "",
    "range": "",
    "positions": [],
    "reach": [],
    "history": []
  },
  {
    "call": "29",
    "part": "(11546389)",
    "desc": "NUT,FLANGED,M6 (NLS.- USE YR00713080)",
    "qty": "1",
    "usage": "",
    "range": "",
    "positions": [],
    "reach": [],
    "history": []
  },
  {
    "call": "30",
    "part": "39179623",
    "desc": "HOSE,ASSY.,FEED",
    "qty": "1",
    "usage": "",
    "range": "",
    "positions": [],
    "reach": [],
    "history": []
  },
  {
    "call": "31",
    "part": "13136378",
    "desc": "-CLIP",
    "qty": "1",
    "usage": "",
    "range": "",
    "positions": [],
    "reach": [],
    "history": []
  },
  {
    "call": "32",
    "part": "90572594",
    "desc": "CLAMP,HOSE,27MM",
    "qty": "1",
    "usage": "",
    "range": "",
    "positions": [],
    "reach": [],
    "history": []
  },
  {
    "call": "33",
    "part": "90572590",
    "desc": "CLAMP,HOSE,23MM",
    "qty": "1",
    "usage": "",
    "range": "",
    "positions": [],
    "reach": [],
    "history": []
  },
  {
    "call": "34",
    "part": "39224971",
    "desc": "HOSE,OUTLET,SURGE TANK",
    "qty": "1",
    "usage": "",
    "range": "",
    "positions": [],
    "reach": [],
    "history": []
  },
  {
    "call": "35",
    "part": "13136378",
    "desc": "-CLIP",
    "qty": "1",
    "usage": "",
    "range": "",
    "positions": [],
    "reach": [],
    "history": []
  },
  {
    "call": "36",
    "part": "90572594",
    "desc": "CLAMP,HOSE,27MM",
    "qty": "3",
    "usage": "",
    "range": "",
    "positions": [],
    "reach": [],
    "history": []
  },
  {
    "call": "37",
    "part": "39207002",
    "desc": "BRACKET",
    "qty": "1",
    "usage": "",
    "range": "",
    "positions": [],
    "reach": [],
    "history": []
  },
  {
    "call": "38",
    "part": "(11588710)",
    "desc": "SCREW,HEX.HD.,M6 X 13 (NLS.- USE YR00161480)",
    "qty": "1",
    "usage": "",
    "range": "",
    "positions": [],
    "reach": [],
    "history": []
  },
  {
    "call": "39",
    "part": "(39238040)",
    "desc": "HOSE (NLS.- USE 39242425)",
    "qty": "1",
    "usage": "",
    "range": "",
    "positions": [],
    "reach": [],
    "history": []
  },
  {
    "call": "40",
    "part": "(90572587)",
    "desc": "CLAMP,HOSE,15MM DIA. (NLS.- USE 90530642 20 94 918)",
    "qty": "1",
    "usage": "",
    "range": "",
    "positions": [],
    "reach": [],
    "history": []
  },
  {
    "call": "41",
    "part": "39238044",
    "desc": "HOSE,ASSY.",
    "qty": "1",
    "usage": "",
    "range": "",
    "positions": [],
    "reach": [],
    "history": []
  },
  {
    "call": "42",
    "part": "90381846",
    "desc": "STRAP,RETAINING",
    "qty": "2",
    "usage": "",
    "range": "",
    "positions": [],
    "reach": [],
    "history": []
  },
  {
    "call": "43",
    "part": "55486411",
    "desc": "HOSE,ASSY.",
    "qty": "1",
    "usage": "",
    "range": "",
    "positions": [],
    "reach": [],
    "history": []
  },
  {
    "call": "44",
    "part": "-HOSE",
    "desc": "",
    "qty": "1",
    "usage": "",
    "range": "",
    "positions": [],
    "reach": [],
    "history": []
  },
  {
    "call": "45",
    "part": "90530642",
    "desc": "-CLAMP,14MM DIA.",
    "qty": "1",
    "usage": "",
    "range": "",
    "positions": [],
    "reach": [],
    "history": []
  },
  {
    "call": "46",
    "part": "55504910",
    "desc": "-SCREW",
    "qty": "1",
    "usage": "",
    "range": "",
    "positions": [],
    "reach": [],
    "history": []
  },
  {
    "call": "47",
    "part": "55497445",
    "desc": "-GASKET",
    "qty": "1",
    "usage": "",
    "range": "",
    "positions": [],
    "reach": [],
    "history": []
  },
  {
    "call": "48",
    "part": "11548168",
    "desc": "SCREW,HEX.HD.,M6X14",
    "qty": "1",
    "usage": "",
    "range": "",
    "positions": [],
    "reach": [],
    "history": []
  },
  {
    "call": "49",
    "part": "55486423",
    "desc": "HOSE,ASSY.,OIL COOLER",
    "qty": "1",
    "usage": "",
    "range": "",
    "positions": [],
    "reach": [],
    "history": []
  },
  {
    "call": "50",
    "part": "90572590",
    "desc": "-CLAMP,HOSE,23MM",
    "qty": "2",
    "usage": "",
    "range": "",
    "positions": [],
    "reach": [],
    "history": []
  },
  {
    "call": "51",
    "part": "(55501995)",
    "desc": "PIPE,ASSY. (NLS.- USE 55515797)",
    "qty": "1",
    "usage": "",
    "range": "",
    "positions": [],
    "reach": [],
    "history": []
  },
  {
    "call": "52",
    "part": "",
    "desc": "-HOSE (AWAITING TECHNICAL RELEASE)",
    "qty": "1",
    "usage": "",
    "range": "",
    "positions": [],
    "reach": [],
    "history": []
  },
  {
    "call": "53",
    "part": "90572590",
    "desc": "-CLAMP,HOSE,23MM",
    "qty": "2",
    "usage": "",
    "range": "",
    "positions": [],
    "reach": [],
    "history": []
  },
  {
    "call": "54",
    "part": "55486416",
    "desc": "GASKET",
    "qty": "1",
    "usage": "",
    "range": "",
    "positions": [],
    "reach": [],
    "history": []
  },
  {
    "call": "55",
    "part": "11548165",
    "desc": "SCREW,HEX.HD.,M5 X 20",
    "qty": "4",
    "usage": "",
    "range": "",
    "positions": [],
    "reach": [],
    "history": []
  }
]